aio_tiny_healthcheck/__init__.py
aio_tiny_healthcheck/__main__.py
aio_tiny_healthcheck/checker.py
aio_tiny_healthcheck/http_server.py
aio_tiny_healthcheck-1.1.3.dist-info/LICENSE
aio_tiny_healthcheck-1.1.3.dist-info/METADATA
aio_tiny_healthcheck-1.1.3.dist-info/WHEEL
aio_tiny_healthcheck-1.1.3.dist-info/RECORD
