Metadata-Version: 2.3
Name: aio-tiny-healthcheck
Version: 1.1.3
Summary: Tiny asynchronous implementation of healthcheck provider and http-server
Author: nikolay.abrosimoff@gmail.com
Requires-Python: >=3.9
Classifier: Programming Language :: Python :: 3
Classifier: Programming Language :: Python :: 3.9
Classifier: Programming Language :: Python :: 3.10
Classifier: Programming Language :: Python :: 3.11
Classifier: Programming Language :: Python :: 3.12
Classifier: Programming Language :: Python :: 3.13
Requires-Dist: aiohttp (>=3.12.12,<4.0.0)
